ai_code_sessions/__init__.py
ai_code_sessions/cli.py
ai_code_sessions/core.py
ai_code_sessions/templates/base.html
ai_code_sessions/templates/index.html
ai_code_sessions/templates/macros.html
ai_code_sessions/templates/master_index.html
ai_code_sessions/templates/page.html
ai_code_sessions/templates/project_index.html
ai_code_sessions/templates/repo_archive.html
ai_code_sessions/templates/search.js
ai_code_sessions-0.1.6.dist-info/licenses/LICENSE
ai_code_sessions-0.1.6.dist-info/WHEEL
ai_code_sessions-0.1.6.dist-info/entry_points.txt
ai_code_sessions-0.1.6.dist-info/METADATA
ai_code_sessions-0.1.6.dist-info/RECORD
