Metadata-Version: 2.4
Name: ai-code-sessions
Version: 0.1.6
Summary: Convert Codex and Claude Code session logs to HTML transcripts
Author: Russ Ronchi, Simon Willison
License-Expression: Apache-2.0
License-File: LICENSE
Requires-Dist: click
Requires-Dist: click-default-group
Requires-Dist: httpx
Requires-Dist: jinja2
Requires-Dist: markdown
Requires-Dist: questionary
Requires-Python: >=3.11
Project-URL: Homepage, https://github.com/hbruss/ai-code-sessions
Project-URL: Upstream, https://github.com/simonw/claude-code-transcripts
